ai_circus/__init__.py
ai_circus/models.py
ai_circus/assistants/baisc_intent_detector_and_retriever.py
ai_circus/assistants/prompts.yaml
ai_circus/core/__init__.py
ai_circus/core/custom_logger.py
ai_circus/core/info.py
ai_circus/tools/check_api_keys.py
ai_circus/tools/generate_commits_messages.py
ai_circus/tools/hello_world.py
ai_circus-0.1.1.dist-info/METADATA
ai_circus-0.1.1.dist-info/WHEEL
ai_circus-0.1.1.dist-info/entry_points.txt
ai_circus-0.1.1.dist-info/licenses/LICENSE
ai_circus-0.1.1.dist-info/RECORD
