Metadata-Version: 2.4
Name: ai-circus
Version: 0.1.1
Summary: Smart AI Building Block for innovative applications.
Project-URL: Homepage, https://github.com/angelmtenor/ai-circus
Project-URL: Repository, https://github.com/angelmtenor/ai-circus
Project-URL: Documentation, https://angelmtenor.github.io/ai-circus
Project-URL: BugTracker, https://github.com/angelmtenor/ai-circus/issues
Author-email: Angel Martinez-Tenor <angelmtenor@gmail.com>
License: MIT
License-File: LICENSE
Keywords: ai,building block,deep learning,machine learning,neural networks,python,smart systems
Classifier: Development Status :: 3 - Alpha
Classifier: Intended Audience :: Developers
Classifier: Intended Audience :: Science/Research
Classifier: License :: OSI Approved :: MIT License
Classifier: Operating System :: OS Independent
Classifier: Programming Language :: Python
Classifier: Programming Language :: Python :: 3
Classifier: Programming Language :: Python :: 3.13
Classifier: Topic :: Scientific/Engineering :: Artificial Intelligence
Classifier: Topic :: Software Development :: Libraries :: Python Modules
Requires-Python: >=3.13
Requires-Dist: gitpython>=3.1.44
Requires-Dist: httpx>=0.28.1
Requires-Dist: langchain-core>=0.3.59
Requires-Dist: langchain-google-genai>=2.1.4
Requires-Dist: langchain-openai>=0.3.16
Requires-Dist: langchain>=0.3.25
Requires-Dist: langgraph>=0.4.3
Requires-Dist: loguru>=0.7.3
Requires-Dist: psutil>=7.0.0
Requires-Dist: py-cpuinfo>=9.0.0
Requires-Dist: pydantic>=2.11.4
Requires-Dist: python-dotenv>=1.1.0
Provides-Extra: optional
